README.rst
setup.py
Aeronaut.egg-info/PKG-INFO
Aeronaut.egg-info/SOURCES.txt
Aeronaut.egg-info/dependency_links.txt
Aeronaut.egg-info/requires.txt
Aeronaut.egg-info/top_level.txt
aeronaut/__init__.py
aeronaut/cloud.py
aeronaut/request/__init__.py
aeronaut/request/cloud/__init__.py
aeronaut/request/cloud/v0_9/__init__.py
aeronaut/request/cloud/v0_9/add_storage_to_server.py
aeronaut/request/cloud/v0_9/clean_failed_server_deployment.py
aeronaut/request/cloud/v0_9/create_acl_rule.py
aeronaut/request/cloud/v0_9/create_network.py
aeronaut/request/cloud/v0_9/delete_acl_rule.py
aeronaut/request/cloud/v0_9/delete_server.py
aeronaut/request/cloud/v0_9/deploy_server.py
aeronaut/request/cloud/v0_9/does_image_name_exist.py
aeronaut/request/cloud/v0_9/get_my_account.py
aeronaut/request/cloud/v0_9/get_server_image.py
aeronaut/request/cloud/v0_9/list_acl_rules.py
aeronaut/request/cloud/v0_9/list_data_centers.py
aeronaut/request/cloud/v0_9/list_images.py
aeronaut/request/cloud/v0_9/list_networks.py
aeronaut/request/cloud/v0_9/list_servers.py
aeronaut/request/cloud/v0_9/modify_server.py
aeronaut/request/cloud/v0_9/poweroff_server.py
aeronaut/request/cloud/v0_9/reboot_server.py
aeronaut/request/cloud/v0_9/request.py
aeronaut/request/cloud/v0_9/reset_server.py
aeronaut/request/cloud/v0_9/server_action.py
aeronaut/request/cloud/v0_9/shutdown_server.py
aeronaut/request/cloud/v0_9/start_server.py
aeronaut/request/cloud/v0_9/update_admin_account.py
aeronaut/resource/__init__.py
aeronaut/resource/cloud/__init__.py
aeronaut/resource/cloud/account.py
aeronaut/resource/cloud/acl.py
aeronaut/resource/cloud/action_status.py
aeronaut/resource/cloud/data_center.py
aeronaut/resource/cloud/disk.py
aeronaut/resource/cloud/image.py
aeronaut/resource/cloud/machine_status.py
aeronaut/resource/cloud/my_account.py
aeronaut/resource/cloud/network.py
aeronaut/resource/cloud/os.py
aeronaut/resource/cloud/resource.py
aeronaut/resource/cloud/server.py
aeronaut/resource/cloud/software_label.py
aircraft/__init__.py
aircraft/params.py
aircraft/request.py
aircraft/response.py
aircraft/value_object.py