Metadata-Version: 1.0
Name: Aeronaut
Version: 0.1.0a3
Summary: Aeronaut: A client library for DiData Cloud
Home-page: UNKNOWN
Author: Nexus IS Dev Team
Author-email: dev@nexusis.com
License: UNKNOWN
Platform: UNKNOWN
